cafe24_sms/__init__.py
cafe24_sms/data.py
cafe24_sms/exceptions.py
cafe24_sms/request.py
cafe24_sms/result_codes.py
cafe24_sms/settings.py
cafe24_sms/shortcuts.py
cafe24_sms/utils.py
cafe24_sms_Django-1.1.0.dist-info/LICENSE
cafe24_sms_Django-1.1.0.dist-info/METADATA
cafe24_sms_Django-1.1.0.dist-info/WHEEL
cafe24_sms_Django-1.1.0.dist-info/top_level.txt
cafe24_sms_Django-1.1.0.dist-info/RECORD
