Metadata-Version: 2.1
Name: cafe24-sms-Django
Version: 1.1.0
Summary: Send SMS messages to mobile devices through Cafe24 SMS api.
Home-page: https://github.com/iumjjing/cafe24-sms-Django
Author: Hyunwoo Shim
Author-email: hyunwoo.shim@laziness.xyz
License: UNKNOWN
Download-URL: https://github.com/iumjjing/cafe24-sms-Django/archive/master.zip
Platform: UNKNOWN
Classifier: Intended Audience :: Developers
Classifier: Operating System :: OS Independent
Classifier: License :: OSI Approved :: MIT License
Classifier: Programming Language :: Python
Classifier: Programming Language :: Python :: 2
Classifier: Programming Language :: Python :: 2.7
Classifier: Programming Language :: Python :: 3
Classifier: Programming Language :: Python :: 3.4
Classifier: Programming Language :: Python :: 3.5
Classifier: Programming Language :: Python :: 3.6
Requires-Dist: Django (>=1.11)
